djangolovessandstorm/__init__.py
djangolovessandstorm/admin.py
djangolovessandstorm/apps.py
djangolovessandstorm/backends.py
djangolovessandstorm/drf.py
djangolovessandstorm/errors.py
djangolovessandstorm/middleware.py
djangolovessandstorm/models.py
djangolovessandstorm/migrations/0001_initial.py
djangolovessandstorm/migrations/__init__.py
djangolovessandstorm-0.0.5.dist-info/LICENSE
djangolovessandstorm-0.0.5.dist-info/METADATA
djangolovessandstorm-0.0.5.dist-info/WHEEL
djangolovessandstorm-0.0.5.dist-info/top_level.txt
djangolovessandstorm-0.0.5.dist-info/RECORD
