Metadata-Version: 2.1
Name: djangolovessandstorm
Version: 0.0.5
Summary: Django-Sandstorm integration
Home-page: http://www.tjf.us/en/code/python/djangolovessandstorm
Author: Troy J. Farrell
Author-email: troy@entheossoft.com
License: BSD-3-Clause
Platform: UNKNOWN
Classifier: Development Status :: 4 - Beta
Classifier: Framework :: Django :: 2.2
Classifier: Programming Language :: Python :: 3.5
Classifier: License :: OSI Approved :: BSD License
Classifier: Natural Language :: English
Classifier: Operating System :: POSIX :: Linux
License-File: LICENSE
Provides-Extra: djangorestframework
Requires-Dist: djangorestframework ; extra == 'djangorestframework'
